syra/__init__.py
syra/cli.py
python_syra-0.5.3.dist-info/AUTHORS
python_syra-0.5.3.dist-info/METADATA
python_syra-0.5.3.dist-info/WHEEL
python_syra-0.5.3.dist-info/entry_points.txt
python_syra-0.5.3.dist-info/top_level.txt
python_syra-0.5.3.dist-info/RECORD
